__init__.py
blacklist_checker/__init__.py
blacklist_checker/cli/__init__.py
blacklist_checker/cli/mycli.py
blacklist_checker/messaging/Mailer.py
blacklist_checker/messaging/__init__.py
blacklist_checker/requester/Black_list_checker.py
blacklist_checker/requester/__init__.py
blacklist_checker-0.0.4.1.dist-info/LICENSE
blacklist_checker-0.0.4.1.dist-info/METADATA
blacklist_checker-0.0.4.1.dist-info/WHEEL
blacklist_checker-0.0.4.1.dist-info/entry_points.txt
blacklist_checker-0.0.4.1.dist-info/top_level.txt
blacklist_checker-0.0.4.1.dist-info/RECORD
