Metadata-Version: 2.1
Name: blacklist-checker
Version: 0.0.4.1
Summary: Check if a specific domain is in mail blaclist 
Author-email: Benoit Chenal <ben57univ@gmail.com>
License: Apache License
Project-URL: Homepage, https://github.com/benochen/blacklist-checker.git
Keywords: blacklist,domain,mail
Classifier: License :: OSI Approved :: MIT License
Classifier: Programming Language :: Python
Classifier: Programming Language :: Python :: 3
Requires-Python: >=3.9
License-File: LICENSE
Requires-Dist: requests
Requires-Dist: typer
Requires-Dist: configparser
Requires-Dist: tomli ; python_version < "3.11"
Provides-Extra: dev
Requires-Dist: black ; extra == 'dev'
Requires-Dist: bumpver ; extra == 'dev'
Requires-Dist: isort ; extra == 'dev'
Requires-Dist: pip-tools ; extra == 'dev'
Requires-Dist: pytest ; extra == 'dev'
